{
  "channel_name": "BBC Radio 2",
  "channel_logo": "https://raw.githubusercontent.com/dp247/mediaportal-uk-logos/master/Radio/BBC-Radio-2.png",
  "schedule": [
    {
      "date": "24 March 2026",
      "programmes": [
        {
          "show_name": "OJ Borg",
          "show_description": "As it's just ticked over into Tuesday, OJ wants to hear about what cheered you up on Monday, the little wins that made it a Blue Sky Monday.",
          "show_logo": "",
          "start_time": "00:00",
          "end_time": "02:30"
        },
        {
          "show_name": "One Hit Wonders with OJ Borg",
          "show_description": "OJ is celebrating 41 years since The Dream Academy released Life In A Northern Town, and heading back to 1985 with Full Force, Sharpe & Numan and The Big Sound Authority.",
          "show_logo": "",
          "start_time": "02:30",
          "end_time": "03:00"
        },
        {
          "show_name": "Dance Sounds of the 90s with Vernon Kay",
          "show_description": "What were you doing in 1992? Vernon has a nostalgia filled soundtrack to take you right back to the best decade in dance, with tunes from Inner City, The Shamen, The Prodigy & more.",
          "show_logo": "",
          "start_time": "03:00",
          "end_time": "04:00"
        },
        {
          "show_name": "Owain Wyn Evans",
          "show_description": "It's Early Breakfast with Owain Wyn Evans, featuring Step Back in Time and Airdrum Anthems. This morning we are asking you about the most memorable TV theme songs!",
          "show_logo": "",
          "start_time": "04:00",
          "end_time": "06:30"
        },
        {
          "show_name": "The Scott Mills Breakfast Show",
          "show_description": "Scott's got your morning sorted... with Sarah Michelle Gellar and Kathryn Newton! Come and play the Birthday Game or take on the Easiest Quiz on the Radio.",
          "show_logo": "",
          "start_time": "06:30",
          "end_time": "09:30"
        },
        {
          "show_name": "Vernon Kay",
          "show_description": "Two listeners take on Vernon's mid-morning music quiz Ten To The Top. Plus, actress Holliday Grainger, star of The Capture, joins Vernon this week to choose her Tracks Of My Years.",
          "show_logo": "",
          "start_time": "09:30",
          "end_time": "12:00"
        },
        {
          "show_name": "Jeremy Vine",
          "show_description": "Jeremy and guests discuss the news headlines and talk to the people making them.",
          "show_logo": "",
          "start_time": "12:00",
          "end_time": "14:00"
        },
        {
          "show_name": "Trevor Nelson",
          "show_description": "Trevor is bringing you some of the best music from across the decades to get you through the afternoon.",
          "show_logo": "",
          "start_time": "14:00",
          "end_time": "16:00"
        },
        {
          "show_name": "Sara Cox",
          "show_description": "Sara gets you through teatime with plenty of giggles and some fab music. Plus Totally Teavoted, the SARA Awards, Lost Four Five Words and Hatched, Matched and Dispatched.",
          "show_logo": "",
          "start_time": "16:00",
          "end_time": "18:30"
        },
        {
          "show_name": "Sara Cox's Half Wower",
          "show_description": "Sara plays the biggest and best tunes to get you up dancing!",
          "show_logo": "",
          "start_time": "18:30",
          "end_time": "19:00"
        },
        {
          "show_name": "Jo Whiley's Shiny Happy Playlist",
          "show_description": "Jo brings her Shiny Happy Playlist, 30 minutes of feel-good music from 7-7.30pm to soundtrack listeners' weekday evening.",
          "show_logo": "",
          "start_time": "19:00",
          "end_time": "19:30"
        },
        {
          "show_name": "Jo Whiley",
          "show_description": "Jo chats to movie critic James King about the latest films you won't want to miss!",
          "show_logo": "",
          "start_time": "19:30",
          "end_time": "21:00"
        },
        {
          "show_name": "The Jazz Show with Jamie Cullum",
          "show_description": "Jamie is live from Maida Vale with the Leeds spiritual jazz group Work Money Death. Plus, tracks from Billie Holiday, George Lewis and Roy Ayers.",
          "show_logo": "",
          "start_time": "21:00",
          "end_time": "22:00"
        },
        {
          "show_name": "The Good Groove with DJ Spoony",
          "show_description": "Feel-good tunes to make you groove! Plus, Jalen Ngonda chooses the tracks that take him back to the dance floors of his youth in Rewind Selector.",
          "show_logo": "",
          "start_time": "22:00",
          "end_time": "00:00"
        }
      ]
    },
    {
      "date": "25 March 2026",
      "programmes": [
        {
          "show_name": "OJ Borg",
          "show_description": "OJ is live through the night from the Salford Riviera and he needs your celebrity puns to build a new team. Plus, Midnight Mastermind, Wish You Were There and Shiftfaced.",
          "show_logo": "",
          "start_time": "00:00",
          "end_time": "03:00"
        },
        {
          "show_name": "Sounds of the 90s with Fearne Cotton",
          "show_description": "Robbie Williams is in charge... anything could happen! He's picking all his favourite 90s tunes, and sharing the memories attached.",
          "show_logo": "",
          "start_time": "03:00",
          "end_time": "04:00"
        },
        {
          "show_name": "Owain Wyn Evans",
          "show_description": "Welcome! It's Early Breakfast with Owain Wyn Evans, featuring our daily time tunnel game: Step Back in time and Airdrum Anthems. This morning we are getting the spring cleaners in!",
          "show_logo": "",
          "start_time": "04:00",
          "end_time": "06:30"
        },
        {
          "show_name": "The Scott Mills Breakfast Show",
          "show_description": "Scott's got your morning sorted... with Niall Horan talking about his new album! Come and play the Birthday Game or take on the Easiest Quiz On The Radio.",
          "show_logo": "",
          "start_time": "06:30",
          "end_time": "09:30"
        },
        {
          "show_name": "Vernon Kay",
          "show_description": "Vernon hears about what's making you smile on Good News Wednesday plus more from actress Holliday Grainger who is choosing her Tracks of My Years all this week.",
          "show_logo": "",
          "start_time": "09:30",
          "end_time": "12:00"
        },
        {
          "show_name": "Jeremy Vine",
          "show_description": "Jeremy and guests discuss the news headlines and talk to the people making them.",
          "show_logo": "",
          "start_time": "12:00",
          "end_time": "14:00"
        },
        {
          "show_name": "Trevor Nelson",
          "show_description": "Trevor is bringing you some of the best music from across the decades to get you through the afternoon.",
          "show_logo": "",
          "start_time": "14:00",
          "end_time": "16:00"
        },
        {
          "show_name": "Sara Cox",
          "show_description": "Sara gets you through teatime with plenty of giggles and some fab music. Plus Totally Teavoted, the SARA Awards, Bunch of 5s and Hatched, Matched and Dispatched.",
          "show_logo": "",
          "start_time": "16:00",
          "end_time": "18:30"
        },
        {
          "show_name": "Sara Cox's Half Wower",
          "show_description": "Sara plays the biggest and best tunes to get you up dancing!",
          "show_logo": "",
          "start_time": "18:30",
          "end_time": "19:00"
        },
        {
          "show_name": "Jo Whiley's Shiny Happy Playlist",
          "show_description": "Jo brings her Shiny Happy Playlist, 30 minutes of feel-good music from 7-7.30pm to soundtrack listeners' weekday evening.",
          "show_logo": "",
          "start_time": "19:00",
          "end_time": "19:30"
        },
        {
          "show_name": "Jo Whiley",
          "show_description": "Blossom Caldarone performs a Sofa Session for Jo, with tracks from her upcoming EP and a cover!",
          "show_logo": "",
          "start_time": "19:30",
          "end_time": "21:00"
        },
        {
          "show_name": "The Folk Show with Mark Radcliffe",
          "show_description": "The best folk and acoustic music. Sean Cooney talks about his project, Peter's Field.",
          "show_logo": "",
          "start_time": "21:00",
          "end_time": "22:00"
        },
        {
          "show_name": "The Good Groove with DJ Spoony",
          "show_description": "Feel-good tunes to make you groove, from soulful house to RnB, disco to doo-wop and everything else in-between. Join in with addictive guessing game 'Music Is The Answer'.",
          "show_logo": "",
          "start_time": "22:00",
          "end_time": "00:00"
        }
      ]
    }
  ]
}