{
  "channel_name": "Film4 ROI",
  "channel_logo": "https://raw.githubusercontent.com/tv-logo/tv-logos/main/countries/united-kingdom/film-4-uk.png",
  "schedule": [
    {
      "date": "14 March 2026",
      "programmes": [
        {
          "show_name": "The Lodge",
          "show_description": "(2019) Horror twist on the fairy-tale paradigm with Riley Keough. A future stepmother tries to gain the trust of her partner's children. But the kids will stop at nothing to get rid.",
          "show_logo": "https://images.metadata.sky.com/pd-image/0a0b18f6-2a99-46a4-8b83-62da06d5e8a0/cover",
          "start_time": "01:50",
          "end_time": "04:00"
        },
        {
          "show_name": "Teleshopping",
          "show_description": "Teleshopping.",
          "show_logo": "",
          "start_time": "04:00",
          "end_time": "06:00"
        },
        {
          "show_name": "Teleshopping",
          "show_description": "Teleshopping.",
          "show_logo": "",
          "start_time": "06:00",
          "end_time": "11:00"
        },
        {
          "show_name": "Annie",
          "show_description": "(2014) Jamie Foxx stars in this reboot of the 1982 musical. Orphan Annie is transported to post-2008 recession-hit New York, where she becomes the ward of a germaphobe running for mayor.",
          "show_logo": "https://images.metadata.sky.com/pd-image/20bdc368-0b36-4586-9d79-80528bb79f50/cover",
          "start_time": "11:00",
          "end_time": "13:20"
        },
        {
          "show_name": "The Longest Day",
          "show_description": "(1962) War drama. Darryl F Zanuck's classic Oscar-winning recreation of the Allied landings in Normandy on 6 June 1944, with an all-star British, American, German and French cast.",
          "show_logo": "https://images.metadata.sky.com/pd-image/28442b97-8402-4c9e-836a-adaa0d205f8a/cover",
          "start_time": "13:20",
          "end_time": "16:55"
        },
        {
          "show_name": "Beast Interview Special",
          "show_description": "Director Michael Pearce and star Jessie Buckley talk about making the dark British drama set on Jersey.",
          "show_logo": "https://images.metadata.sky.com/pd-image/a22322a0-8fd4-381f-b3e0-b66facd225b8/cover",
          "start_time": "16:55",
          "end_time": "17:05"
        },
        {
          "show_name": "Made in Italy",
          "show_description": "(2020) Comedy-drama with Liam Neeson. An estranged father and son team up to fix up and sell an old Tuscan villa that their late wife and mother left to them.",
          "show_logo": "https://images.metadata.sky.com/pd-image/19b37966-a164-4760-9e39-e8a6956ee2a9/cover",
          "start_time": "17:05",
          "end_time": "18:55"
        },
        {
          "show_name": "Ticket to Paradise",
          "show_description": "(2022) Romcom with Julia Roberts and George Clooney. A staggeringly beautiful, divorced couple reunite to stop their daughter's wedding in the staggeringly beautiful surroundings of Bali.",
          "show_logo": "https://images.metadata.sky.com/pd-image/2941d951-b933-4a88-9be9-bde1de194e8a/cover",
          "start_time": "18:55",
          "end_time": "21:00"
        },
        {
          "show_name": "Erin Brockovich",
          "show_description": "(2000) Fact-based legal drama. Julia Roberts won an Oscar, Golden Globe and BAFTA for her portrayal of a single mum making a huge impact at a legal firm despite having no formal training.",
          "show_logo": "https://images.metadata.sky.com/pd-image/5b048c32-5c36-40e3-b84b-e98df317c80b/cover",
          "start_time": "21:00",
          "end_time": "23:40"
        },
        {
          "show_name": "The Hunt",
          "show_description": "(2020) Fighty, satirical horror that upset Donald Trump. Hilary Swank plays a rich lefty who likes hunting working class people to the death. But she didn't reckon on Betty Gilpin.",
          "show_logo": "https://images.metadata.sky.com/pd-image/72db79ee-7aca-4393-a186-0bb772ba7d4e/cover",
          "start_time": "23:40",
          "end_time": "01:25"
        }
      ]
    },
    {
      "date": "15 March 2026",
      "programmes": [
        {
          "show_name": "American Refugee",
          "show_description": "(2021) Zeitgeisty survival thriller. When the American economy tanks, oil prices plummet and the borders close, people start to panic...",
          "show_logo": "https://images.metadata.sky.com/pd-image/26acffdc-8c65-3420-be9a-267bd3521b01/cover",
          "start_time": "01:25",
          "end_time": "03:15"
        },
        {
          "show_name": "Teleshopping",
          "show_description": "Teleshopping.",
          "show_logo": "",
          "start_time": "03:15",
          "end_time": "06:00"
        },
        {
          "show_name": "Teleshopping",
          "show_description": "Teleshopping.",
          "show_logo": "",
          "start_time": "06:00",
          "end_time": "11:00"
        },
        {
          "show_name": "Steel Magnolias",
          "show_description": "(1989) Star-studded tragi-comedy with Julia Roberts, Daryl Hannah, Dolly Parton and more. Six Southern belles console and cajole each other through life in a Louisiana beauty parlour.",
          "show_logo": "https://images.metadata.sky.com/pd-image/ac4ebfa5-2ed3-4972-997d-55a8f3b3aab7/cover",
          "start_time": "11:00",
          "end_time": "13:20"
        },
        {
          "show_name": "Beast Interview Special",
          "show_description": "Director Michael Pearce and star Jessie Buckley talk about making the dark British drama set on Jersey.",
          "show_logo": "https://images.metadata.sky.com/pd-image/a22322a0-8fd4-381f-b3e0-b66facd225b8/cover",
          "start_time": "13:20",
          "end_time": "13:30"
        },
        {
          "show_name": "Jumanji: The Next Level",
          "show_description": "(2019) Adventure comedy sequel with Dwayne Johnson, Jack Black, Kevin Hart and Karen Gillan. The old school pals enter the Jumanji video game again to save their friend.",
          "show_logo": "https://images.metadata.sky.com/pd-image/ae956eff-0817-4a9b-b6c9-707bed10a9f3/cover",
          "start_time": "13:30",
          "end_time": "15:50"
        },
        {
          "show_name": "Howards End",
          "show_description": "(1992) Anthony Hopkins, Helena Bonham Carter and Emma Thompson star in James Ivory's adaptation of EM Forster's novel about two families, love, treachery and revenge.",
          "show_logo": "https://images.metadata.sky.com/pd-image/20b20b87-15df-4a1a-aef8-5b1a6fa920b3/cover",
          "start_time": "15:50",
          "end_time": "18:40"
        },
        {
          "show_name": "Beast Interview Special",
          "show_description": "Director Michael Pearce and star Jessie Buckley talk about making the dark British drama set on Jersey.",
          "show_logo": "https://images.metadata.sky.com/pd-image/a22322a0-8fd4-381f-b3e0-b66facd225b8/cover",
          "start_time": "18:40",
          "end_time": "18:50"
        },
        {
          "show_name": "Knight and Day",
          "show_description": "(2010) Action-comedy starring Tom Cruise and Cameron Diaz. A CIA assassin kidnaps a woman and takes her on an impromptu round-the-world trip in order to save both their lives. Violence.",
          "show_logo": "https://images.metadata.sky.com/pd-image/bb2097fe-0f75-49af-baec-d8876c2ee46b/cover",
          "start_time": "18:50",
          "end_time": "21:00"
        },
        {
          "show_name": "The Equalizer 2",
          "show_description": "(2018) Action crime thriller sequel. Denzel Washington returns as Robert McCall, who's out for revenge after ruthless killers murder an agency contact who he also considered a friend.",
          "show_logo": "https://images.metadata.sky.com/pd-image/b9e42ea4-464b-4763-af2a-96052a045cbf/cover",
          "start_time": "21:00",
          "end_time": "23:20"
        },
        {
          "show_name": "The Infernal Machine",
          "show_description": "(2022) Thriller starring Guy Pearce as a writer-in-hiding whose novel inspired a teenager to kill 13 people 25 years ago. And now he must revisit the past.",
          "show_logo": "https://images.metadata.sky.com/pd-image/f027cea9-f39e-4fad-af40-ed4e8554bc65/cover",
          "start_time": "23:20",
          "end_time": "01:30"
        }
      ]
    }
  ]
}