{
  "channel_name": "GB News HD",
  "channel_logo": "https://raw.githubusercontent.com/tv-logo/tv-logos/main/countries/united-kingdom/gb-news-uk.png",
  "schedule": [
    {
      "date": "31 March 2026",
      "programmes": [
        {
          "show_name": "The Late Show Live",
          "show_description": "Live from Washington DC, Bev Turner and Ben Leo bring you the latest from the US and what it means for Britain.",
          "show_logo": "https://images.metadata.sky.com/pd-image/f6d49f62-0cd3-4f89-9880-6a93946870db/cover",
          "start_time": "00:00",
          "end_time": "03:00"
        },
        {
          "show_name": "Patrick Christys Tonight",
          "show_description": "Join Patrick for two hours of spirited debate and news making interviews. Top guests tackle the issues that matter, with a sharp take on every story.",
          "show_logo": "https://images.metadata.sky.com/pd-image/f177f724-25d8-4eb7-b1a2-c7076c5b8384/cover",
          "start_time": "03:00",
          "end_time": "05:00"
        },
        {
          "show_name": "Patrick Christys Tonight Late...",
          "show_description": "Edition. Tomorrow's news, tonight. All the major stories making the front pages and full coverage of all the breaking news at home and abroad with Patrick Christys.",
          "show_logo": "https://images.metadata.sky.com/pd-image/6047ab67-c581-4211-9b2e-d0925521a582/cover",
          "start_time": "05:00",
          "end_time": "06:00"
        },
        {
          "show_name": "Breakfast with Eamonn and Ellie",
          "show_description": "Join Eamonn Holmes & Ellie Costello to start your day across the United Kingdom. This is your breakfast show. Join the conversation about what is happening in our nation and the world.",
          "show_logo": "https://images.metadata.sky.com/pd-image/b063c56e-2110-4bb1-beda-e242fbf894ff/cover",
          "start_time": "06:00",
          "end_time": "09:30"
        },
        {
          "show_name": "Britain's Newsroom",
          "show_description": "Andrew and Miriam present Monday to Thursday mornings. When the news happens, it happens here. GB News brings you the biggest stories and the answers you need from across the UK.",
          "show_logo": "https://images.metadata.sky.com/pd-image/e0ac9bfc-2a8f-4526-b4a6-ed787b6fc117/cover",
          "start_time": "09:30",
          "end_time": "12:00"
        },
        {
          "show_name": "Good Afternoon Britain",
          "show_description": "Tackling the big stories from all angles and perspectives. Weekdays from midday, Tom Harwood and Nana Akua bring you the most compelling stories from across the United Kingdom.",
          "show_logo": "https://images.metadata.sky.com/pd-image/e0281822-c1f5-4569-ad46-b7631138f4a0/cover",
          "start_time": "12:00",
          "end_time": "15:00"
        },
        {
          "show_name": "Martin Daubney",
          "show_description": "Join Martin for an up-to-the-minute take on the day's events delivered in his own unique and lively style.",
          "show_logo": "https://images.metadata.sky.com/pd-image/7925204d-cbdc-40da-b6c8-2af4e54c0b38/cover",
          "start_time": "15:00",
          "end_time": "18:00"
        },
        {
          "show_name": "Dewbs & Co",
          "show_description": "Plain-speaking, straight-talking - Michelle delivers her individual take on the day's news.",
          "show_logo": "https://images.metadata.sky.com/pd-image/78160fac-748f-4c92-99f6-fd7c17db4704/cover",
          "start_time": "18:00",
          "end_time": "19:00"
        },
        {
          "show_name": "GBN Tonight",
          "show_description": "The day's biggest stories debated and dissected, GBN Tonight brings you hard-hitting interviews and expert analysis on everything that matters.",
          "show_logo": "https://images.metadata.sky.com/pd-image/911d35fd-8f13-4f48-83d5-9fee4fcc589c/cover",
          "start_time": "19:00",
          "end_time": "20:00"
        },
        {
          "show_name": "Jacob Rees-Mogg's State Of The Nation",
          "show_description": "Join Jacob for his unique and unmissable take on the day's news.",
          "show_logo": "https://images.metadata.sky.com/pd-image/05ea01a2-7c4d-4cfc-be28-5f164b9148b8/cover",
          "start_time": "20:00",
          "end_time": "21:00"
        },
        {
          "show_name": "Patrick Christys Tonight",
          "show_description": "Join Patrick for two hours of spirited debate and news making interviews. Top guests tackle the issues that matter, with a sharp take on every story.",
          "show_logo": "https://images.metadata.sky.com/pd-image/4ceec384-d40f-41d8-92a7-db3b8d59f697/cover",
          "start_time": "21:00",
          "end_time": "23:00"
        },
        {
          "show_name": "Patrick Christys Tonight Late...",
          "show_description": "Edition. Tomorrow's news, tonight. All the major stories making the front pages and full coverage of all the breaking news at home and abroad with Patrick Christys.",
          "show_logo": "https://images.metadata.sky.com/pd-image/54c89a2a-9289-4eaa-be5c-3e53d2ee822c/cover",
          "start_time": "23:00",
          "end_time": "00:00"
        }
      ]
    },
    {
      "date": "1 April 2026",
      "programmes": [
        {
          "show_name": "The Late Show Live",
          "show_description": "Live from Washington DC, Bev Turner and Ben Leo bring you the latest from the US and what it means for Britain.",
          "show_logo": "https://images.metadata.sky.com/pd-image/73667d80-209a-4b0c-801d-8da8ee936bd1/cover",
          "start_time": "00:00",
          "end_time": "03:00"
        },
        {
          "show_name": "Patrick Christys Tonight",
          "show_description": "Join Patrick for two hours of spirited debate and news making interviews. Top guests tackle the issues that matter, with a sharp take on every story.",
          "show_logo": "https://images.metadata.sky.com/pd-image/37708866-faa2-4f7a-97e3-e2edca344a6d/cover",
          "start_time": "03:00",
          "end_time": "05:00"
        },
        {
          "show_name": "Patrick Christys Tonight Late...",
          "show_description": "Edition. Tomorrow's news, tonight. All the major stories making the front pages and full coverage of all the breaking news at home and abroad with Patrick Christys.",
          "show_logo": "https://images.metadata.sky.com/pd-image/6961b198-c85e-4997-9610-ea0c3318f2f8/cover",
          "start_time": "05:00",
          "end_time": "06:00"
        },
        {
          "show_name": "Breakfast with Eamonn and Ellie",
          "show_description": "Join Eamonn Holmes & Ellie Costello to start your day across the United Kingdom. This is your breakfast show. Join the conversation about what is happening in our nation and the world.",
          "show_logo": "https://images.metadata.sky.com/pd-image/b456890d-ac31-4f2d-ac93-9061aa0f5a7b/cover",
          "start_time": "06:00",
          "end_time": "09:30"
        },
        {
          "show_name": "Britain's Newsroom",
          "show_description": "Andrew and Miriam present Monday to Thursday mornings. When the news happens, it happens here. GB News brings you the biggest stories and the answers you need from across the UK.",
          "show_logo": "https://images.metadata.sky.com/pd-image/1b679659-99a6-47e0-8d51-b6d6d16db759/cover",
          "start_time": "09:30",
          "end_time": "12:00"
        },
        {
          "show_name": "Good Afternoon Britain",
          "show_description": "Tackling the big stories from all angles and perspectives. Tom Harwood and Nana Akua bring you the most compelling stories from across the United Kingdom.",
          "show_logo": "https://images.metadata.sky.com/pd-image/f616010e-6bfe-4973-8671-ca67b67cdd94/cover",
          "start_time": "12:00",
          "end_time": "15:00"
        },
        {
          "show_name": "Martin Daubney",
          "show_description": "Join Martin for an up-to-the-minute take on the day's events delivered in his own unique and lively style.",
          "show_logo": "https://images.metadata.sky.com/pd-image/311d69ae-ea9e-4483-b6e7-4d157c258d88/cover",
          "start_time": "15:00",
          "end_time": "18:00"
        },
        {
          "show_name": "Dewbs & Co",
          "show_description": "Plain-speaking, straight-talking - Michelle delivers her individual take on the day's news.",
          "show_logo": "https://images.metadata.sky.com/pd-image/01bbe2d2-9128-4f9a-a192-994caef996ff/cover",
          "start_time": "18:00",
          "end_time": "19:00"
        },
        {
          "show_name": "GBN Tonight",
          "show_description": "The day's biggest stories debated and dissected, GBN Tonight brings you hard-hitting interviews and expert analysis on everything that matters.",
          "show_logo": "https://images.metadata.sky.com/pd-image/27d0bd9b-28db-4eca-afce-e4c5884670e2/cover",
          "start_time": "19:00",
          "end_time": "20:00"
        },
        {
          "show_name": "Jacob Rees-Mogg's State Of The Nation",
          "show_description": "Join Jacob for his unique and unmissable take on the day's news.",
          "show_logo": "https://images.metadata.sky.com/pd-image/7c409933-953d-478e-99c3-463e0c9ab2b3/cover",
          "start_time": "20:00",
          "end_time": "21:00"
        },
        {
          "show_name": "Patrick Christys Tonight",
          "show_description": "Join Patrick for two hours of spirited debate and news making interviews. Top guests tackle the issues that matter, with a sharp take on every story.",
          "show_logo": "https://images.metadata.sky.com/pd-image/77182c19-ab59-4f07-a565-22772ce8a7c7/cover",
          "start_time": "21:00",
          "end_time": "23:00"
        },
        {
          "show_name": "Patrick Christys Tonight Late...",
          "show_description": "Edition. Tomorrow's news, tonight. All the major stories making the front pages and full coverage of all the breaking news at home and abroad with Patrick Christys.",
          "show_logo": "https://images.metadata.sky.com/pd-image/a628bb8c-569b-4474-9bb3-c8e032169c5b/cover",
          "start_time": "23:00",
          "end_time": "00:00"
        }
      ]
    }
  ]
}