{
  "channel_name": "True Crime+1",
  "channel_logo": "https://raw.githubusercontent.com/dp247/mediaportal-uk-logos/master/TV/True-Crime-%2B1.png",
  "schedule": [
    {
      "date": "24 March 2026",
      "programmes": [
        {
          "show_name": "Bloodline Detectives",
          "show_description": "A woman in Texas is killed and left in an old cellar. Can new forensic science tools find the murderer? S5, Ep20",
          "show_logo": "https://images.metadata.sky.com/pd-image/606898e6-5dc8-4f13-b008-211155913ad0/cover",
          "start_time": "00:00",
          "end_time": "01:00"
        },
        {
          "show_name": "Judge Judy",
          "show_description": "A woman hires her housekeeper to clean her entire house in exchange for furniture in her storage unit, but claims she took the wrong items. S24, Ep24",
          "show_logo": "https://images.metadata.sky.com/pd-image/79a5c568-1dd0-4082-923b-664894237df1/cover",
          "start_time": "01:00",
          "end_time": "01:25"
        },
        {
          "show_name": "Judge Judy",
          "show_description": "A woman claims her friend loves to donate money to help care for dogs in distress, so she owes her nothing. S24, Ep25",
          "show_logo": "https://images.metadata.sky.com/pd-image/a434606a-c968-4a1b-b289-1cfbf1e30c02/cover",
          "start_time": "01:25",
          "end_time": "01:50"
        },
        {
          "show_name": "Judge Judy",
          "show_description": "A real estate broker plays a voice message that clearly states that her web designer agrees to return her deposit. S24, Ep26",
          "show_logo": "https://images.metadata.sky.com/pd-image/834fc9f3-6d3a-428d-a3d0-b842cd1f09e0/cover",
          "start_time": "01:50",
          "end_time": "02:15"
        },
        {
          "show_name": "Judge Judy",
          "show_description": "A woman claims she was shot in the eye with a liquid sprayer at a grocery store and is still suffering; she sues for damages. S22, Ep151",
          "show_logo": "https://images.metadata.sky.com/pd-image/22315b99-9680-4aca-8d35-ced96960e402/cover",
          "start_time": "02:15",
          "end_time": "02:40"
        },
        {
          "show_name": "Judge Judy",
          "show_description": "A woman is accused of stealing money from her deceased mother's savings account; her stepfather sues her for payback. S22, Ep152",
          "show_logo": "https://images.metadata.sky.com/pd-image/3232e355-a595-4640-a108-a8551d94c922/cover",
          "start_time": "02:40",
          "end_time": "03:05"
        },
        {
          "show_name": "Judge Judy",
          "show_description": "Children's visits to prison to see their convicted father are at the heart of a case between his sister and the daycare provider who escorted them. S22, Ep153",
          "show_logo": "https://images.metadata.sky.com/pd-image/55c30c03-d6e1-4b42-96ba-857b459f99ad/cover",
          "start_time": "03:05",
          "end_time": "03:30"
        },
        {
          "show_name": "Judge Judy",
          "show_description": "A man returns home to find his beloved Dachshund maimed and bleeding in a neighbour's backyard. S22, Ep154",
          "show_logo": "https://images.metadata.sky.com/pd-image/a9148d67-d389-4fba-b091-47e2dd1a1b2a/cover",
          "start_time": "03:30",
          "end_time": "03:55"
        },
        {
          "show_name": "Judge Judy",
          "show_description": "A landlord accuses his teen tenant's boyfriend of head-butting him during an altercation; when he pushes back, the police are called. S22, Ep155",
          "show_logo": "https://images.metadata.sky.com/pd-image/e9e324a4-4fde-4487-95ce-4b60c5899b36/cover",
          "start_time": "03:55",
          "end_time": "04:20"
        },
        {
          "show_name": "Judge Judy",
          "show_description": "Concerned about the fate of a Pomeranian puppy, a breeder drives 6 hours to rescue the animal from an allegedly negligent pet owner. S22, Ep156",
          "show_logo": "https://images.metadata.sky.com/pd-image/8a4b180f-4b55-4fe3-8fd9-f5d00948e81e/cover",
          "start_time": "04:20",
          "end_time": "04:45"
        },
        {
          "show_name": "Judge Judy",
          "show_description": "A woman being sued by her ex-lover for the return of his belongings claims she had to sell them to survive. S22, Ep157",
          "show_logo": "https://images.metadata.sky.com/pd-image/454bb574-3567-4757-bf2e-67d63e9e33e3/cover",
          "start_time": "04:45",
          "end_time": "05:10"
        },
        {
          "show_name": "Judge Judy",
          "show_description": "The alleged death of a woman and her baby in a head-on collision is called into question when a social worker sues an aspiring singer for check fraud. S16, Ep56",
          "show_logo": "https://images.metadata.sky.com/pd-image/834b8abf-a4a7-4393-b949-7024b02f92c6/cover",
          "start_time": "05:10",
          "end_time": "05:35"
        },
        {
          "show_name": "Facing Evil",
          "show_description": "Bruce Kellogg is shot four times while sleeping. The shooter is 19-year-old Denver McDowell who says he was put up to it by the victim's wife - 26-year-old Laurie Kellogg. S4, Ep3",
          "show_logo": "https://images.metadata.sky.com/pd-image/98b16809-570d-4bd8-b8e1-7940e9f2d405/cover",
          "start_time": "05:35",
          "end_time": "05:55"
        },
        {
          "show_name": "Close Calls: On Camera",
          "show_description": "A teacher out for a walk with her dog risks her own life to save her pet. S3, Ep2",
          "show_logo": "https://images.metadata.sky.com/pd-image/f9711467-7029-4682-80a1-3bb26acab9e0/cover",
          "start_time": "05:55",
          "end_time": "06:20"
        },
        {
          "show_name": "Close Calls: On Camera",
          "show_description": "When a mountain biker suffers a freak accident, a total stranger comes to his aid. S3, Ep3",
          "show_logo": "https://images.metadata.sky.com/pd-image/846072c4-ab45-4724-9719-4a1e6e6634a2/cover",
          "start_time": "06:20",
          "end_time": "07:00"
        },
        {
          "show_name": "Teleshopping",
          "show_description": "Innovative, value-for-money products brought directly to you at home. Shop 'til you drop whilst avoiding the hustle and bustle of the High Street.",
          "show_logo": "",
          "start_time": "07:00",
          "end_time": "10:00"
        },
        {
          "show_name": "Judge Judy",
          "show_description": "Two Chihuahuas are found dead after a neighbour's American Bullies allegedly bust through a doggie door and attack them. S22, Ep123",
          "show_logo": "https://images.metadata.sky.com/pd-image/087c6f04-3292-4b21-baa7-f4e1032ecf53/cover",
          "start_time": "10:00",
          "end_time": "10:25"
        },
        {
          "show_name": "Judge Judy",
          "show_description": "A woman accuses her landlord of inappropriate behaviour; she denies owing him for rent and breaking her lease. S22, Ep124",
          "show_logo": "https://images.metadata.sky.com/pd-image/5ae1088b-26ef-48f0-bab7-6b770dc817e1/cover",
          "start_time": "10:25",
          "end_time": "10:50"
        },
        {
          "show_name": "Judge Judy",
          "show_description": "The Judge discovers an intriguing story of alleged fraud and vandalism when an unsuspecting motorist calls for help. S22, Ep125",
          "show_logo": "https://images.metadata.sky.com/pd-image/277efd29-b2b9-4942-82a7-63117a05ae29/cover",
          "start_time": "10:50",
          "end_time": "11:15"
        },
        {
          "show_name": "Judge Judy",
          "show_description": "After a couple is asked to pay up for an unauthorised tenant, they complain about leaks, mould and sewage issues. S22, Ep126",
          "show_logo": "https://images.metadata.sky.com/pd-image/33ea39ef-b703-4fc2-ae93-07e0e154e7b7/cover",
          "start_time": "11:15",
          "end_time": "11:40"
        },
        {
          "show_name": "Judge Judy",
          "show_description": "A woman claims she sent racy pictures of herself in a negligee with another man to her ex-boyfriend and that's why she's being sued for his impounded car which she totalled. S16, Ep10",
          "show_logo": "https://images.metadata.sky.com/pd-image/ffee892f-6b24-40ce-8f7c-5789c430cffd/cover",
          "start_time": "11:40",
          "end_time": "12:05"
        },
        {
          "show_name": "Judge Judy",
          "show_description": "Inspection of a man's handwriting, defamation of character and an alleged assault come into play when ex-friends fight over repossession of a truck. S16, Ep11",
          "show_logo": "https://images.metadata.sky.com/pd-image/5d179b8d-a51e-49a4-b7e9-0c350db88f21/cover",
          "start_time": "12:05",
          "end_time": "12:30"
        },
        {
          "show_name": "Judge Judy",
          "show_description": "A home-based Internet business, a divorce, and an ex-employee caught in the middle come into play when ex-roommates fight over rent. S16, Ep12",
          "show_logo": "https://images.metadata.sky.com/pd-image/37a8abf2-f5d9-4214-9bcf-ea07b582914a/cover",
          "start_time": "12:30",
          "end_time": "13:00"
        },
        {
          "show_name": "Judge Judy",
          "show_description": "Claiming she made over $7,000 in car payments, a young woman sues her ex-stepfather after he repossesses her vehicle. S16, Ep13",
          "show_logo": "https://images.metadata.sky.com/pd-image/43d58e23-461c-495e-8991-b94d942906ac/cover",
          "start_time": "13:00",
          "end_time": "13:30"
        },
        {
          "show_name": "Judge Judy",
          "show_description": "The Judge questions a woman's courtroom attitude when she is sued by her ex-best friend for the value of a car and her personal belongings. S24, Ep27",
          "show_logo": "https://images.metadata.sky.com/pd-image/95b3259d-431c-411c-a1df-321d2b185066/cover",
          "start_time": "13:30",
          "end_time": "14:00"
        },
        {
          "show_name": "Judge Judy",
          "show_description": "A woman admits that she only knew a man for 24 hours before she invited him home; she says the ex-con kidnapped her and forced her to co-sign on a truck loan. S24, Ep28",
          "show_logo": "https://images.metadata.sky.com/pd-image/8aa29de8-c831-4ce7-89bd-3dc349db9275/cover",
          "start_time": "14:00",
          "end_time": "14:30"
        },
        {
          "show_name": "Judge Judy",
          "show_description": "An allegedly scorned woman warns her ex's new girlfriend not to date a man for a multitude of reasons; he accuses her of trespassing and harassment. S24, Ep29",
          "show_logo": "https://images.metadata.sky.com/pd-image/89274eb6-2f7f-4eab-81a4-716f6b2a98e5/cover",
          "start_time": "14:30",
          "end_time": "15:00"
        },
        {
          "show_name": "Judge Judy",
          "show_description": "A woman sues an alleged slumlord for injuries she received while on his property; his defence is that she should have seen the hole. S22, Ep158",
          "show_logo": "https://images.metadata.sky.com/pd-image/6d465822-03af-4c56-8393-6476d4335129/cover",
          "start_time": "15:00",
          "end_time": "15:30"
        },
        {
          "show_name": "Judge Judy",
          "show_description": "A barter agreement to purchase a motorcycle ends with an unhappy seller who claims he received stolen merchandise and four flat tires. S22, Ep159",
          "show_logo": "https://images.metadata.sky.com/pd-image/bbc65173-4982-4345-b917-af899bba507c/cover",
          "start_time": "15:30",
          "end_time": "16:00"
        },
        {
          "show_name": "Judge Judy",
          "show_description": "A woman claims she was forced to euthanise her seven-week-old German Shepherd puppy; she sues the man who sold the animal to her. S22, Ep160",
          "show_logo": "https://images.metadata.sky.com/pd-image/f73a9e3c-057f-404f-bcac-b55c721f608b/cover",
          "start_time": "16:00",
          "end_time": "16:30"
        },
        {
          "show_name": "Judge Judy",
          "show_description": "An expecting mother allows her boyfriend to send risqué photos of them together to his ex-girlfriend who allegedly punches her in the head. S22, Ep161",
          "show_logo": "https://images.metadata.sky.com/pd-image/a29aa46c-a8a9-4568-ae7f-a5fe15bb4a31/cover",
          "start_time": "16:30",
          "end_time": "17:00"
        },
        {
          "show_name": "Judge Judy",
          "show_description": "A woman sues her ex-fiancé for an alleged loan to pay off his debt; he claims he spent plenty of money on her when they were together. S22, Ep162",
          "show_logo": "https://images.metadata.sky.com/pd-image/b399a5ef-4cee-49d2-80ed-ac95e8a87d71/cover",
          "start_time": "17:00",
          "end_time": "17:25"
        },
        {
          "show_name": "Judge Judy",
          "show_description": "After a woman accuses her estranged husband of using corporal punishment on their children, he turns to a new 'girlfriend' for help with a divorce attorney. S22, Ep163",
          "show_logo": "https://images.metadata.sky.com/pd-image/5a8da737-f1ff-4fdf-acb2-7e58d1cee628/cover",
          "start_time": "17:25",
          "end_time": "17:50"
        },
        {
          "show_name": "Judge Judy",
          "show_description": "A woman asks her nanny for thousands of dollars in order to send her 8-year-old daughter to cheerleading camp; her nanny wants payback. S22, Ep164",
          "show_logo": "https://images.metadata.sky.com/pd-image/24a993ea-eff3-4e50-9520-7edc82c4558b/cover",
          "start_time": "17:50",
          "end_time": "18:15"
        },
        {
          "show_name": "Judge Judy",
          "show_description": "A dog perishes in an apartment fire caused by the pet's owner; the renter then sues the landlord and contractor for damages to his belongings. S16, Ep26",
          "show_logo": "https://images.metadata.sky.com/pd-image/80e84cd2-332d-4d14-afda-c6bc7ef17b40/cover",
          "start_time": "18:15",
          "end_time": "18:40"
        },
        {
          "show_name": "Judge Judy",
          "show_description": "A poker party ends in thousands of dollars in alleged damages when a married couple finds deep scratches on their hardwood floor; they blame a card dealer. S16, Ep27",
          "show_logo": "https://images.metadata.sky.com/pd-image/8f2720ce-31ac-4fc5-a2f8-9038688a680a/cover",
          "start_time": "18:40",
          "end_time": "19:05"
        },
        {
          "show_name": "Judge Judy",
          "show_description": "A second DUI leaves a woman with 320 hours of community service to complete; she claims a pastor swindled her into free labour. S16, Ep28",
          "show_logo": "https://images.metadata.sky.com/pd-image/6923914c-df02-4a77-8947-275f2cd60f0c/cover",
          "start_time": "19:05",
          "end_time": "19:30"
        },
        {
          "show_name": "Judge Judy",
          "show_description": "A PTA president sues the father of a promising scholarship winner after he fails to get her on the bus for a prestigious tour of colleges. S16, Ep29",
          "show_logo": "https://images.metadata.sky.com/pd-image/d484c9c3-8e64-46a0-87d9-504f35d6aa2f/cover",
          "start_time": "19:30",
          "end_time": "20:00"
        },
        {
          "show_name": "Murder UK",
          "show_description": "Shane Gilmer and Laura Sugden were planning a quiet night out when a horrific ambush shattered their lives. S2, Ep9",
          "show_logo": "https://images.metadata.sky.com/pd-image/4eb427f7-cf45-4a48-939d-d1dbd5e1280c/cover",
          "start_time": "20:00",
          "end_time": "21:00"
        },
        {
          "show_name": "Fraud Squad",
          "show_description": "The hunt is on for a ruthless fantasist who has defrauded our NHS of thousands. S2, Ep2",
          "show_logo": "https://images.metadata.sky.com/pd-image/6a1afe88-e3f8-4f4e-8ed6-548cc01e7514/cover",
          "start_time": "21:00",
          "end_time": "22:00"
        },
        {
          "show_name": "Storm of Suspicion",
          "show_description": "When a young woman vanishes during one of the worst droughts in California history, detectives embark on a decades-long investigation to find a serial killer. S3, Ep21",
          "show_logo": "https://images.metadata.sky.com/pd-image/30821543-d282-4ed3-951e-ada509760239/cover",
          "start_time": "22:00",
          "end_time": "23:00"
        },
        {
          "show_name": "Killers: Caught on Camera",
          "show_description": "In the US, a missing 15-year-old is found by cadaver dogs. In the UK, a mystery needs to be solved to identify a dismembered body in a suitcase. S1, Ep2",
          "show_logo": "https://images.metadata.sky.com/pd-image/8f2b74f3-19d4-4c03-b9bf-0cc84c98786e/cover",
          "start_time": "23:00",
          "end_time": "00:00"
        }
      ]
    },
    {
      "date": "25 March 2026",
      "programmes": [
        {
          "show_name": "Bloodline Detectives",
          "show_description": "In 2024, Pamela Wittman, a 25-year-old from Indiana, was identified, solving the 1980 Daytona Beach cold case linked to a serial killer. S6, Ep1",
          "show_logo": "https://images.metadata.sky.com/pd-image/75fe71d2-6a62-4160-9116-f3b341417005/cover",
          "start_time": "00:00",
          "end_time": "01:00"
        },
        {
          "show_name": "Judge Judy",
          "show_description": "The Judge questions a woman's courtroom attitude when she is sued by her ex-best friend for the value of a car and her personal belongings. S24, Ep27",
          "show_logo": "https://images.metadata.sky.com/pd-image/1eeaecce-c7df-4375-a793-0eee456c9e1e/cover",
          "start_time": "01:00",
          "end_time": "01:25"
        },
        {
          "show_name": "Judge Judy",
          "show_description": "A woman admits that she only knew a man for 24 hours before she invited him home; she says the ex-con kidnapped her and forced her to co-sign on a truck loan. S24, Ep28",
          "show_logo": "https://images.metadata.sky.com/pd-image/f3e95a56-6c89-4004-b681-feb5cb986b17/cover",
          "start_time": "01:25",
          "end_time": "01:50"
        },
        {
          "show_name": "Judge Judy",
          "show_description": "An allegedly scorned woman warns her ex's new girlfriend not to date a man for a multitude of reasons; he accuses her of trespassing and harassment. S24, Ep29",
          "show_logo": "https://images.metadata.sky.com/pd-image/52e28cd6-03cc-468d-be86-8c3b1652a552/cover",
          "start_time": "01:50",
          "end_time": "02:15"
        },
        {
          "show_name": "Judge Judy",
          "show_description": "A woman sues an alleged slumlord for injuries she received while on his property; his defence is that she should have seen the hole. S22, Ep158",
          "show_logo": "https://images.metadata.sky.com/pd-image/57932afd-ddc3-42ab-be78-ad4dbd352f30/cover",
          "start_time": "02:15",
          "end_time": "02:40"
        },
        {
          "show_name": "Judge Judy",
          "show_description": "A barter agreement to purchase a motorcycle ends with an unhappy seller who claims he received stolen merchandise and four flat tires. S22, Ep159",
          "show_logo": "https://images.metadata.sky.com/pd-image/8bd85713-6d7b-4235-a7db-89ba3463538e/cover",
          "start_time": "02:40",
          "end_time": "03:05"
        },
        {
          "show_name": "Judge Judy",
          "show_description": "A woman claims she was forced to euthanise her seven-week-old German Shepherd puppy; she sues the man who sold the animal to her. S22, Ep160",
          "show_logo": "https://images.metadata.sky.com/pd-image/ced6e5a6-a553-4db1-a5a3-bbce20a67cbb/cover",
          "start_time": "03:05",
          "end_time": "03:30"
        },
        {
          "show_name": "Judge Judy",
          "show_description": "An expecting mother allows her boyfriend to send risqué photos of them together to his ex-girlfriend who allegedly punches her in the head. S22, Ep161",
          "show_logo": "https://images.metadata.sky.com/pd-image/c02e17d6-56f4-40cd-a20e-0cb7b1b294d0/cover",
          "start_time": "03:30",
          "end_time": "03:55"
        },
        {
          "show_name": "Judge Judy",
          "show_description": "A woman sues her ex-fiancé for an alleged loan to pay off his debt; he claims he spent plenty of money on her when they were together. S22, Ep162",
          "show_logo": "https://images.metadata.sky.com/pd-image/3291cbbf-a80a-428f-9966-e8645635ec45/cover",
          "start_time": "03:55",
          "end_time": "04:20"
        },
        {
          "show_name": "Judge Judy",
          "show_description": "After a woman accuses her estranged husband of using corporal punishment on their children, he turns to a new 'girlfriend' for help with a divorce attorney. S22, Ep163",
          "show_logo": "https://images.metadata.sky.com/pd-image/e9c0dc6a-08ee-4b11-94ea-f6cfc45c634b/cover",
          "start_time": "04:20",
          "end_time": "04:45"
        },
        {
          "show_name": "Judge Judy",
          "show_description": "A woman asks her nanny for thousands of dollars in order to send her 8-year-old daughter to cheerleading camp; her nanny wants payback. S22, Ep164",
          "show_logo": "https://images.metadata.sky.com/pd-image/d78b6b24-82ea-4291-a070-496bf9334b69/cover",
          "start_time": "04:45",
          "end_time": "05:10"
        },
        {
          "show_name": "Judge Judy",
          "show_description": "A man says he had a horrible vacation in Puerto Rico and sues his former friend for the cost of the trip; she claims he invited her and had romantic intentions. S16, Ep57",
          "show_logo": "https://images.metadata.sky.com/pd-image/788d6700-0255-4f3e-911d-32463c870a8d/cover",
          "start_time": "05:10",
          "end_time": "05:35"
        },
        {
          "show_name": "Facing Evil",
          "show_description": "Dental records identify a decomposing body as 23-year-old Marine Sergeant Elihue Parker. The prosecution says Elihue's estranged wife Kimberly Parker ordered his execution. S4, Ep4",
          "show_logo": "https://images.metadata.sky.com/pd-image/d7f962be-c3dd-4e54-9db8-df472b769019/cover",
          "start_time": "05:35",
          "end_time": "05:55"
        },
        {
          "show_name": "Close Calls: On Camera",
          "show_description": "A family on a safari holiday is attacked by an elephant as they sit down to eat. S3, Ep6",
          "show_logo": "https://images.metadata.sky.com/pd-image/61c9107b-ef00-4713-81cd-a1050fc0621b/cover",
          "start_time": "05:55",
          "end_time": "06:20"
        },
        {
          "show_name": "Close Calls: On Camera",
          "show_description": "A paraglider pilot plunges 6,000 feet and lands 60 feet up in the tree canopy. S3, Ep4",
          "show_logo": "https://images.metadata.sky.com/pd-image/785c1784-0d1a-4df4-9089-4594fe7a86b1/cover",
          "start_time": "06:20",
          "end_time": "07:00"
        },
        {
          "show_name": "Teleshopping",
          "show_description": "Innovative, value-for-money products brought directly to you at home. Shop 'til you drop whilst avoiding the hustle and bustle of the High Street.",
          "show_logo": "",
          "start_time": "07:00",
          "end_time": "10:00"
        },
        {
          "show_name": "Judge Judy",
          "show_description": "When a retired pest control worker sprays insect killer on a shared tree, his neighbours claim they suffered serious respiratory injury. S22, Ep130",
          "show_logo": "https://images.metadata.sky.com/pd-image/c9be18bc-9e48-4801-bac8-bac78d35932d/cover",
          "start_time": "10:00",
          "end_time": "10:25"
        },
        {
          "show_name": "Judge Judy",
          "show_description": "A writer claims she submitted articles that her editor never paid her for; he says the writing was not factual, and that he wasn't paid by his clients. S22, Ep131",
          "show_logo": "https://images.metadata.sky.com/pd-image/7b00728e-bf01-4f45-a28e-2b8fab31a2f1/cover",
          "start_time": "10:25",
          "end_time": "10:50"
        },
        {
          "show_name": "Judge Judy",
          "show_description": "A woman demands thousands in payback for a valuable truck; her friend says she traded an antique, hand carved oak table for the vehicle. S22, Ep132",
          "show_logo": "https://images.metadata.sky.com/pd-image/d45341f9-6902-4029-9987-bf643a8ded55/cover",
          "start_time": "10:50",
          "end_time": "11:15"
        },
        {
          "show_name": "Judge Judy",
          "show_description": "A daycare provider says her attempt to improve a playground resulted in substandard concrete work; she sues for damages. S22, Ep133",
          "show_logo": "https://images.metadata.sky.com/pd-image/cc64fcef-1934-4073-a008-432a5e2a6fbf/cover",
          "start_time": "11:15",
          "end_time": "11:40"
        },
        {
          "show_name": "Judge Judy",
          "show_description": "A senior citizen is accused of assaulting another senior at a Ladies' Auxiliary VFW meeting and is escorted out of her hotel room by police. She sues for damages. S16, Ep14",
          "show_logo": "https://images.metadata.sky.com/pd-image/74f5c3f4-76ed-4112-bab4-2fc0face066c/cover",
          "start_time": "11:40",
          "end_time": "12:05"
        },
        {
          "show_name": "Judge Judy",
          "show_description": "After meeting a mechanic at a bowling alley, a woman ends up suing him for allegedly selling her broken-down BMW without her permission; he claims he was forced to get rid of it. S16, Ep15",
          "show_logo": "https://images.metadata.sky.com/pd-image/28189077-3f47-4048-a6fb-60230af5e136/cover",
          "start_time": "12:05",
          "end_time": "12:30"
        },
        {
          "show_name": "Judge Judy",
          "show_description": "A mother's allegedly inappropriate behaviour with her daughter's fiancé, drinking problems and damage caused by Chihuahuas come into play in a fight over fishing poles. S16, Ep16",
          "show_logo": "https://images.metadata.sky.com/pd-image/c321cdce-12c0-4c55-b4b6-e50fb6c36f4c/cover",
          "start_time": "12:30",
          "end_time": "13:00"
        },
        {
          "show_name": "Judge Judy",
          "show_description": "After ruining her credit, a woman demands that her boyfriend's adult son return the car she co-signed for him or give her money to pay it off. S16, Ep17",
          "show_logo": "https://images.metadata.sky.com/pd-image/c0e6eb24-8aff-4396-99c8-131fd883b758/cover",
          "start_time": "13:00",
          "end_time": "13:30"
        },
        {
          "show_name": "Judge Judy",
          "show_description": "A woman claims her ex-boyfriend slashed her tyres but fails to prove a word of her story; he is still in the hot seat for alleged theft of her property. S24, Ep30",
          "show_logo": "https://images.metadata.sky.com/pd-image/cf33e511-99c2-4cc6-97cb-1cbd5f6409aa/cover",
          "start_time": "13:30",
          "end_time": "14:00"
        },
        {
          "show_name": "Judge Judy",
          "show_description": "Sad news is delivered in the midst of a fight between ex-roommates over ruined credit and alleged identity theft. S24, Ep31",
          "show_logo": "https://images.metadata.sky.com/pd-image/7fa0a1f8-e90b-439f-8f6c-bc3bad0b5690/cover",
          "start_time": "14:00",
          "end_time": "14:30"
        },
        {
          "show_name": "Judge Judy",
          "show_description": "A legally-blind woman is court ordered to take anger management classes after slapping her husband; she sues the class owner for unpaid wages. S24, Ep32",
          "show_logo": "https://images.metadata.sky.com/pd-image/b1550826-8b03-4ad2-991d-571db2334792/cover",
          "start_time": "14:30",
          "end_time": "15:00"
        },
        {
          "show_name": "Judge Judy",
          "show_description": "A man claims he was attacked in a sober-living facility; his housemate says he was leaving the stove on overnight to heat the place. S22, Ep165",
          "show_logo": "https://images.metadata.sky.com/pd-image/8432be8c-60d6-4c41-ad89-11a48a249cf3/cover",
          "start_time": "15:00",
          "end_time": "15:30"
        },
        {
          "show_name": "Judge Judy",
          "show_description": "Two women with children by the same man go after each other in a fight over defamation and loss of income; a third potential baby mama comes into play. S22, Ep166",
          "show_logo": "https://images.metadata.sky.com/pd-image/c79baa90-e468-4636-b4ec-bbc02bdb86e4/cover",
          "start_time": "15:30",
          "end_time": "16:00"
        },
        {
          "show_name": "Judge Judy",
          "show_description": "A single father claims he had no choice but to take heroic efforts to protect his home from Hurricane Irma and used public property to do so. S22, Ep167",
          "show_logo": "https://images.metadata.sky.com/pd-image/989e0a68-e7de-4859-80a8-599d0f5f0f74/cover",
          "start_time": "16:00",
          "end_time": "16:30"
        },
        {
          "show_name": "Judge Judy",
          "show_description": "The Judge reads a woman the riot act when she allegedly uses the family court system to evict a tenant by means of a questionable restraining order. S22, Ep168",
          "show_logo": "https://images.metadata.sky.com/pd-image/0feff083-ee83-4407-9ab1-642337e91832/cover",
          "start_time": "16:30",
          "end_time": "17:00"
        },
        {
          "show_name": "Judge Judy",
          "show_description": "When a German Shepherd puppy dies, pet owners blame the breeder; the Judge investigates allegations of parvo running rampant in the litter. S22, Ep169",
          "show_logo": "https://images.metadata.sky.com/pd-image/7c86ca26-eb6b-4ec6-bb43-7c0b242b2b67/cover",
          "start_time": "17:00",
          "end_time": "17:25"
        },
        {
          "show_name": "Judge Judy",
          "show_description": "A man denies having intimate relations with a woman; she claims he lived with her for two months and assaulted her daughter. S22, Ep170",
          "show_logo": "https://images.metadata.sky.com/pd-image/39f30d42-7982-4e5a-b914-b6220f558c84/cover",
          "start_time": "17:25",
          "end_time": "17:50"
        },
        {
          "show_name": "Judge Judy",
          "show_description": "A woman goes after her estranged daughter-in-law for thousands in unpaid loans; she is met with rage over an allegedly deadbeat husband. S22, Ep171",
          "show_logo": "https://images.metadata.sky.com/pd-image/dd1c7898-ac0a-492d-84c1-079119004014/cover",
          "start_time": "17:50",
          "end_time": "18:15"
        },
        {
          "show_name": "Judge Judy",
          "show_description": "Afraid that her intoxicated friend was about to be raped, a woman claims she pushed through an already broken window to rescue her; she is sued for breaking the window. S16, Ep30",
          "show_logo": "https://images.metadata.sky.com/pd-image/f20258aa-fc14-4a43-b346-333b14cd0325/cover",
          "start_time": "18:15",
          "end_time": "18:40"
        },
        {
          "show_name": "Judge Judy",
          "show_description": "Accused of being a crook after allegedly selling a $500 rug for $7500, a carpet shop owner denies all charges and insists the married couple was satisfied at the time of their purchase. S16, Ep31",
          "show_logo": "https://images.metadata.sky.com/pd-image/ee6ba291-7658-489d-9926-d126045f4f7e/cover",
          "start_time": "18:40",
          "end_time": "19:05"
        },
        {
          "show_name": "Judge Judy",
          "show_description": "A teenager accuses a teacher of punching him in the chest during an incident at school; the teacher countersues for attorney fees and punitive damages. S16, Ep32",
          "show_logo": "https://images.metadata.sky.com/pd-image/8250f821-832e-4c37-bc66-481a66d2dcd6/cover",
          "start_time": "19:05",
          "end_time": "19:30"
        },
        {
          "show_name": "Judge Judy",
          "show_description": "Teenagers brawl in a parking lot and the police are called in; damages from alleged kicking, spitting on and keying cars are disputed. S16, Ep33",
          "show_logo": "https://images.metadata.sky.com/pd-image/672cb401-f8b9-4a43-8061-a047e10e6a3a/cover",
          "start_time": "19:30",
          "end_time": "20:00"
        },
        {
          "show_name": "Murder UK",
          "show_description": "In June 2010, taxi driver Derrick Bird went on one of the worst killing sprees in British history. He shot dead twelve people and injured many more. S2, Ep10",
          "show_logo": "https://images.metadata.sky.com/pd-image/3e65f9e1-0d70-4f12-bd92-7c7ebf50cbe7/cover",
          "start_time": "20:00",
          "end_time": "21:00"
        },
        {
          "show_name": "Fraud Squad",
          "show_description": "A wealthy manager is taking the NHS for a ride; and a tax fraudster claims to be a spy. S2, Ep3",
          "show_logo": "https://images.metadata.sky.com/pd-image/dbe6b212-ae30-4b23-b760-71c8e4103fa9/cover",
          "start_time": "21:00",
          "end_time": "22:00"
        },
        {
          "show_name": "Storm of Suspicion",
          "show_description": "As Hurricane Isabel approaches the Virginia Coast, the burned body of a woman is found. S3, Ep22",
          "show_logo": "https://images.metadata.sky.com/pd-image/ab20bb80-6199-4935-af00-6327c4473a06/cover",
          "start_time": "22:00",
          "end_time": "23:00"
        },
        {
          "show_name": "Fatal Fraud",
          "show_description": "A couple set up a weapons business in West Virginia. All is not what it seems, leading to a fatal end. S1, Ep2",
          "show_logo": "https://images.metadata.sky.com/pd-image/b0cb64d8-b270-46c7-9379-bdecc3279187/cover",
          "start_time": "23:00",
          "end_time": "00:00"
        }
      ]
    }
  ]
}